maxhttp/__init__.py
maxhttp/_version.py
maxhttp/auth.py
maxhttp/client.py
maxhttp/connection.py
maxhttp/cookies.py
maxhttp/errors.py
maxhttp/formdata.py
maxhttp/http2.py
maxhttp/logging.py
maxhttp/pool.py
maxhttp/request.py
maxhttp/response.py
maxhttp/retry.py
maxhttp/sync.py
maxhttp/timeouts.py
maxhttp/websocket.py
maxhttp/wsproto/__init__.py
maxhttp-0.1.9.dist-info/licenses/LICENSE
maxhttp-0.1.9.dist-info/METADATA
maxhttp-0.1.9.dist-info/WHEEL
maxhttp-0.1.9.dist-info/top_level.txt
maxhttp-0.1.9.dist-info/RECORD
